{
  "2018-iniziale-1-1": "Ist. “E.Majorana”",
  "2018-iniziale-2-1": "Ist. “E.Majorana”",
  "2018-iniziale-3-1": "Casa Circondariale di Brindisi",
  "2018-iniziale-4-1": "I.I.S.S. MAJORANA",
  "2018-iniziale-5-1": "IISS MAJORANA",
  "2018-iniziale-6-1": "I.I.S.S. MAJORANA",
  "2018-iniziale-7-1": "IPSIA FERRARIS",
  "2018-iniziale-8-1": "IPSIA FERRARIS",
  "2018-iniziale-9-1": "Ist. Ferraris",
  "2018-iniziale-10-1": "Ist. De Marco",
  "2018-iniziale-11-1": "Ist. Palumbo",
  "2018-iniziale-12-1": "Ist. Palumbo",
  "2018-finale-1-1": "Casa Circondariale di Brindisi",
  "2018-finale-2-1": "I.I.S.S. MAJORANA",
  "2018-finale-3-1": "IISS MAJORANA",
  "2018-finale-4-1": "I.I.S.S. MAJORANA",
  "2018-finale-5-1": "IPSIA FERRARIS",
  "2018-finale-6-1": "IPSIA FERRARIS",
  "2018-finale-7-1": "Ist. Ferraris",
  "2018-finale-8-1": "Ist. De Marco",
  "2018-finale-9-1": "Ist. Palumbo",
  "2018-finale-10-1": "Ist. Palumbo",
  "2018-finale-11-1": "Ist. “E.Majorana”",
  "2018-finale-12-1": "Ist. “E.Majorana”"
}